coding_assistant/__init__.py
coding_assistant/__main__.py
coding_assistant/assistant.py
coding_assistant/cli.py
coding_assistant/clipy.py
coding_assistant-0.1.0.dist-info/LICENSE
coding_assistant-0.1.0.dist-info/METADATA
coding_assistant-0.1.0.dist-info/WHEEL
coding_assistant-0.1.0.dist-info/entry_points.txt
coding_assistant-0.1.0.dist-info/top_level.txt
coding_assistant-0.1.0.dist-info/RECORD
