Metadata-Version: 2.1
Name: coding-assistant
Version: 0.1.0
Summary: Recreate the joys of Office Assistant from the comfort of the Python interpreter
Home-page: https://github.com/lorlouis/coding-assistant
Author: Louis Sven Goulet
Author-email: louis.sven@gmail.com
License: UNKNOWN
Platform: UNKNOWN
Classifier: Programming Language :: Python :: 3
Classifier: License :: OSI Approved :: MIT License
Classifier: Operating System :: OS Independent
Requires-Python: >=3.9
License-File: LICENSE
